ml_automation_tool/__init__.py
ml_automation_tool/data_loader.py
ml_automation_tool/evaluator.py
ml_automation_tool/gui_main.py
ml_automation_tool/models.py
ml_automation_tool/utils.py
ml_automation_tool-1.0.0.dist-info/METADATA
ml_automation_tool-1.0.0.dist-info/WHEEL
ml_automation_tool-1.0.0.dist-info/entry_points.txt
ml_automation_tool-1.0.0.dist-info/top_level.txt
ml_automation_tool-1.0.0.dist-info/RECORD
